Metadata-Version: 1.0
Name: bulkrename
Version: 1.0.2
Summary: Rename multiple files in a folder to random characters
Home-page: https://github.com/AlexFlipnote/bulkrename
Author: AlexFlipnote
Author-email: UNKNOWN
License: GNU v3
Platform: UNKNOWN
